{
 "actions": [],
 "allow_rename": 1,
 "creation": "2024-06-10 11:53:10.617232",
 "doctype": "DocType",
 "editable_grid": 1,
 "engine": "InnoDB",
 "field_order": [
  "student",
  "study_type",
  "discount_type",
  "amount",
  "amount_after_discount"
 ],
 "fields": [
  {
   "fieldname": "student",
   "fieldtype": "Link",
   "in_list_view": 1,
   "label": "Student",
   "options": "Student",
   "reqd": 1
  },
  {
   "fieldname": "study_type",
   "fieldtype": "Select",
   "in_list_view": 1,
   "label": "Study Type",
   "options": "Morning\nEvening",
   "reqd": 1
  },
  {
   "fieldname": "discount_type",
   "fieldtype": "Link",
   "in_list_view": 1,
   "label": "Discount Type",
   "options": "Constant"
  },
  {
   "fieldname": "amount",
   "fieldtype": "Float",
   "in_list_view": 1,
   "label": "Amount",
   "reqd": 1
  },
  {
   "fieldname": "amount_after_discount",
   "fieldtype": "Float",
   "in_list_view": 1,
   "label": "Amount After Discount",
   "reqd": 1
  }
 ],
 "index_web_pages_for_search": 1,
 "istable": 1,
 "links": [],
 "modified": "2024-06-23 11:44:53.943772",
 "modified_by": "Administrator",
 "module": "Kalima",
 "name": "Students Fees Table",
 "owner": "Administrator",
 "permissions": [],
 "sort_field": "modified",
 "sort_order": "DESC",
 "states": []
}